Workbook

Sheet BS
A1: Balance sheet
B2: 2021 | C2: 2020 | D2: 2019 | E2: 2018 | F2: 2017
A3: Assets
A4: Cash and balances with treasury banks 5 | B4: 89432245 | C4: 73651718 | D4: 63039290 | E4: 49187645 | F4: 44239325
A5: Balances with other banks 6 | B5: 3556215 | C5: 8196147 | D5: 7886702 | E5: 4093402 | F5: 3193835
A6: Lendings to financial institutions 7 | B6: – | C6: – | D6: 20405972 | E6: – | F6: 2250000
A7: Investments 8 | B7: 616231172 | C7: 449611987 | D7: 305435633 | E7: 260233987 | F7: 314956748
A8: Advances 9 | B8: 477673022 | C8: 395416055 | D8: 372913863 | E8: 343107147 | F8: 258693086
A9: Fixed assets 10 | B9: 20179222 | C9: 21232750 | D9: 19696568 | E9: 12791827 | F9: 9885958
A10: Intangible assets 11 | B10: 1188985 | C10: 1158857 | D10: 808994 | E10: 741361 | F10: 842869
A11: Deferred tax assets 12 | B11: 5161697 | C11: 1597334 | D11: 2489752 | E11: 3773779 | F11: 100755
A12: Other assets 13 | B12: 45906052 | C12: 42021813 | D12: 40450512 | E12: 32522174 | F12: 28448099
B13: 1259328610 | C13: 992886661 | D13: 833443027 | E13: 706666079 | F13: 662938624
A14: Liabilities
A15: Bills payable 14 | B15: 10235374 | C15: 12629996 | D15: 15768947 | E15: 15512880 | F15: 10769262
A16: Borrowings 15 | B16: 123563761 | C16: 84163669 | D16: 51187681 | E16: 52702323 | F16: 71587311
A17: Deposits and other accounts 16 | B17: 1015162254 | C17: 790982287 | D17: 679246312 | E17: 573596926 | F17: 525805051
A18: Liabilities against assets subject to finance lease | B18: – | C18: – | D18: – | E18: – | F18: –
A19: Subordinated debts 17 | B19: 12000000 | C19: 12000000 | D19: 9992000 | E19: 9993600 | F19: 4992800
A20: Deferred tax liabilities | B20: – | C20: – | D20: – | E20: – | F20: –
A21: Other liabilities 18 | B21: 42326358 | C21: 38429434 | D21: 34704048 | E21: 21178476 | F21: 17098223
B22: 1203287747 | C22: 938205386 | D22: 791040844 | E22: 673065718 | F22: 630393388
A23: Net Assets | B23: 56040863 | C23: 54681275 | D23: 42402183 | E23: 33600361 | F23: 332545236
A24: Share capital 19 | B24: 12602602 | C24: 12602602 | D24: 12602602 | E24: 12602602 | F24: 12602602
A25: Reserves | B25: 32832051 | C25: 25701665 | D25: 19408889 | E25: 15588694 | F25: 12139921
A26: Surplus on revaluation of assets - net of tax 20 | B26: 1987976 | C26: 7670955 | D26: 4339893 | E26: 1654920 | F26: 5162131
A27: Unappropriated profit | B27: 8618234 | C27: 8706053 | D27: 6002253 | E27: 3710867 | F27: 2703887
A28: Total equity | B28: 56040863 | C28: 54681275 | D28: 42353637 | E28: 33557083 | F28: 32500883

Sheet IS
B1: Income statement
C2: 2021 | D2: 2020 | E2: 2019 | F2: 2018 | G2: 2017
B3: Mark-up / return / interest earned 23 | C3: 77569443 | D3: 79118320 | E3: 71704373 | F3: 43669883 | G3: 36267220
B4: Mark-up / return / interest expensed 24 | C4: 45139897 | D4: 48842539 | E4: 49567851 | F4: 25059925 | G4: 20071958
B5: Net mark-up / interest income | C5: 32429546 | D5: 30275781 | E5: 22136522 | F5: 18609958 | G5: 17246397
B6: Non mark-up / interest income
B7: Fee and commission income 25 | C7: 4785268 | D7: 3991285 | E7: 3616428 | F7: 3116070 | G7: 2706794
B8: Dividend income | C8: 421964 | D8: 273524 | E8: 274440 | F8: 231312 | G8: 302894
B9: Foreign exchange income | C9: 3123524 | D9: 2673493 | E9: 2507707 | F9: 1596027 | G9: 843032
B10: Income / (loss) from derivatives | C10: – | D10: – | E10: – | F10: – | G10: -
B11: Gain on securities 26 | C11: 814724 | D11: 2555400 | E11: 739351 | F11: 260103 | G11: 2063043
B12: Other income 27 | C12: 402118 | D12: 349438 | E12: 266102 | F12: 418081 | G12: 347470
B13: Total non-markup / interest income | C13: 9547598 | D13: 9843140 | E13: 7404028 | F13: 5621593 | G13: 6263233
B14: Total income | C14: 41977144 | D14: 40118921 | E14: 29540550 | F14: 24231551 | G14: 23509630
B15: Non mark-up / interest expenses
B16: Operating expenses 28 | C16: 21017376 | D16: 20217974 | E16: 18235061 | F16: 16430676 | G16: 14948796
B17: Workers’ welfare fund 29 | C17: 213484 | D17: 42982 | E17: 42117 | F17: -540060 | G17: 21832
B18: Other charges 30 | C18: 90139 | D18: 48149 | E18: 99947 | F18: 905 | G18: 193401
B19: Total non-markup / interest expenses | C19: 21320999 | D19: 20309105 | E19: 18377125 | F19: 15891521 | G19: 15164029
B20: Profit before provisions | C20: 20656145 | D20: 19809816 | E20: 11163425 | F20: 8340030 | G20: 7169169
B21: Provisions and write offs - net 31 | C21: 4983944 | D21: 1974747 | E21: 773275 | F21: 1460575 | G21: -176432
B22: Extraordinary / unusual items | C22: – | D22: – | E22: – | F22: – | G22: –
B23: Profit before taxation | C23: 15672201 | D23: 17835069 | E23: 10390150 | F23: 6879455 | G23: 8345601
B24: Taxation 32 | C24: -5956468 | D24: -6978072 | E24: -3372249 | F24: -2448177 | G24: -3223915
B25: Profit after taxation | C25: 9715733 | D25: 10856997 | E25: 7032570 | F25: 4428619 | G25: 5128297
B26: Attributable to:
B27: Equity holders of the Bank | C27: 9715733 | D27: 10846333 | E27: 7028756 | F27: 4429310 | G27: 5121863
B28: Non-controlling interest | C28: – | D28: 10664 | E28: 3814 | F28: -691 | G28: 6434
C29: 9715733 | D29: 10856997 | E29: 7032570 | F29: 4428619 | G29: 5128297

Sheet Working
A1: Askari Bank (ratio)
F4: 2021 | G4: 2020 | H4: 2019 | I4: 2018 | J4: 2017
A5: 1)Return on Equity=Net income/Total equity
A6: Net income | F6: 9715733 | G6: 10856997 | H6: 7032570 | I6: 4428619 | J6: 5128297
A7: Total equity | F7: 56040863 | G7: 54681275 | H7: 42353637 | I7: 33557083 | J7: 32500883
A8: ROE: | F8: =(F6/F7)*100 -> 17.34 | G8: =(G6/G7)*100 -> 19.86 | H8: =(H6/H7)*100 -> 16.60 | I8: =(I6/I7)*100 -> 13.20 | J8: =(J6/J7)*100 -> 15.78
A10: 2)Return on Asset=Net income/Total Asset
A11: Net income | F11: 9715733 | G11: 10856997 | H11: 7032570 | I11: 4428619 | J11: 5128297
A12: Total asset | F12: 1259328610 | G12: 992886661 | H12: 833443027 | I12: 706666079 | J12: 662938624
A13: ROA: | F13: =(F11/F12)*100 -> 0.77 | G13: =(G11/G12)*100 -> 1.09 | H13: =(H11/H12)*100 -> 0.84 | I13: =(I11/I12)*100 -> 0.63 | J13: =(J11/J12)*100 -> 0.77
A15: 3)Earnings per share
A16: Net income after tax | F16: 9715733 | G16: 10856997 | H16: 7032570 | I16: 4428619 | J16: 5128297
A17: Shares outstanding | F17: 12602602 | G17: 12602602 | H17: 12602602 | I17: 12602602 | J17: 12602602
A18: EPS: | F18: =F16/F17 -> 0.77 | G18: =G16/G17 -> 0.86 | H18: =H16/H17 -> 0.56 | I18: =I16/I17 -> 0.35 | J18: =J16/J17 -> 0.41
A20: 4)Net interest margin=(Interest income-Interest expense)/TA
A21: Interst income | F21: 77569443 | G21: 79118320 | H21: 71704373 | I21: 43669883 | J21: 36267220
A22: Interest expernse | F22: 45139897 | G22: 48842539 | H22: 49567851 | I22: 25059925 | J22: 20071958
A23: Total Asset | F23: 1259328610 | G23: 992886661 | H23: 833443027 | I23: 706666079 | J23: 662938624
A24: Non interest margin | F24: =((F21-F22)/F23)*100 -> 2.58 | G24: =((G21-G22)/G23)*100 -> 3.05 | H24: =((H21-H22)/H23)*100 -> 2.66 | I24: =((I21-I22)/I23)*100 -> 2.63 | J24: =((J21-J22)/J23)*100 -> 2.44
A26: 4)Net NON interest margin=(Non interest revenue-PLLL-Non interest expense)/TA
A27: Non interest revenue | F27: 9547598 | G27: 9843140 | H27: 7404028 | I27: 5621593 | J27: 6263233
A28: Provison for loss/writeoff | F28: 4983944 | G28: 1974747 | H28: 773275 | I28: 1460575 | J28: -176432
A29: Non interest expense | F29: 21320999 | G29: 20309105 | H29: 18377125 | I29: 15891521 | J29: 15164029
A30: Total Asset | F30: 1259328610 | G30: 992886661 | H30: 833443027 | I30: 706666079 | J30: 662938624
A31: Non interest margin | F31: =((F27-F28-F29)/F30)*100 -> -1.33 | G31: =((G27-G28-G29)/G30)*100 -> -1.25 | H31: =((H27-H28-H29)/H30)*100 -> -1.41 | I31: =((I27-I28-I29)/I30)*100 -> -1.66 | J31: =((J27-J28-J29)/J30)*100 -> -1.32
A33: 5)Earning spread
A34: Total interest income | F34: 77569443 | G34: 79118320 | H34: 71704373 | I34: 43669883 | J34: 36267220
A35: Total earning asset | F35: =SUM(BS!B6:B7) -> 616,231,172 | G35: =SUM(BS!C6:C7) -> 449,611,987 | H35: =SUM(BS!D6:D7) -> 325,841,605 | I35: =SUM(BS!E6:E7) -> 260,233,987 | J35: =SUM(BS!F6:F7) -> 317,206,748
A37: Total interest expense | F37: 45139897 | G37: 48842539 | H37: 49567851 | I37: 25059925 | J37: 20071958
A38: Total interest bearing liability(Borrowings+Depostits-Current account) | F38: =SUM(BS!B16:B17) -> 1,138,726,015 | G38: =SUM(BS!C16:C17) -> 875,145,956 | H38: =SUM(BS!D16:D17) -> 730,433,993 | I38: =SUM(BS!E16:E17) -> 626,299,249 | J38: =SUM(BS!F16:F17) -> 597,392,362
A39: Earning spread: | F39: =(F34/F35)-(F37/F38) -> 9% | G39: =(G34/G35)-(G37/G38) -> 12% | H39: =(H34/H35)-(H37/H38) -> 15% | I39: =(I34/I35)-(I37/I38) -> 13% | J39: =(J34/J35)-(J37/J38) -> 8%

Sheet ROE
A4: ROE
B5: 2021 | C5: 2020 | D5: 2019 | E5: 2018 | F5: 2017
A6: Method 1 | B6: =([1]IS!C25/[1]IS!C23)*([1]IS!C23/[1]IS!C14)*([1]IS!C14/[1]BS!B13)*([1]BS!B13/[1]BS!B28) -> #ERROR! | C6: =([1]IS!D25/[1]IS!D23)*([1]IS!D23/[1]IS!D14)*([1]IS!D14/[1]BS!C13)*([1]BS!C13/[1]BS!C28) -> #ERROR! | D6: =([1]IS!E25/[1]IS!E23)*([1]IS!E23/[1]IS!E14)*([1]IS!E14/[1]BS!D13)*([1]BS!D13/[1]BS!D28) -> #ERROR! | E6: =([1]IS!F25/[1]IS!F23)*([1]IS!F23/[1]IS!F14)*([1]IS!F14/[1]BS!E13)*([1]BS!E13/[1]BS!E28) -> #ERROR! | F6: =([1]IS!G25/[1]IS!G23)*([1]IS!G23/[1]IS!G14)*([1]IS!G14/[1]BS!F13)*([1]BS!F13/[1]BS!F28) -> #ERROR!
A7: Method 2 | B7: =[1]Working!F13*([1]BS!B13/[1]BS!B28) -> #ERROR! | C7: =[1]Working!G13*([1]BS!C13/[1]BS!C28) -> #ERROR! | D7: =[1]Working!H13*([1]BS!D13/[1]BS!D28) -> #ERROR! | E7: =[1]Working!I13*([1]BS!E13/[1]BS!E28) -> #ERROR! | F7: =[1]Working!J13*([1]BS!F13/[1]BS!F28) -> #ERROR!
A8: Method 3 | B8: =([1]IS!C25/[1]IS!C14)*([1]IS!C14/[1]BS!B13)*([1]BS!B13/[1]BS!B28) -> #ERROR! | C8: =([1]IS!D25/[1]IS!D14)*([1]IS!D14/[1]BS!C13)*([1]BS!C13/[1]BS!C28) -> #ERROR! | D8: =([1]IS!E25/[1]IS!E14)*([1]IS!E14/[1]BS!D13)*([1]BS!D13/[1]BS!D28) -> #ERROR! | E8: =([1]IS!F25/[1]IS!F14)*([1]IS!F14/[1]BS!E13)*([1]BS!E13/[1]BS!E28) -> #ERROR! | F8: =([1]IS!G25/[1]IS!G14)*([1]IS!G14/[1]BS!F13)*([1]BS!F13/[1]BS!F28) -> #ERROR!
B10: 0.1132 | C10: 0.08 | D10: 0.1345 | E10: 0.06 | F10: 0.06 | G10: Average T bills rate
B11: =B6-B10 -> #ERROR! | C11: =C6-C10 -> #ERROR! | D11: =+D6-D10 -> #ERROR! | E11: =E6-E10 -> #ERROR! | F11: =F6-F10 -> #ERROR! | G11: Market Risk

Sheet Liquidity Risk Measures 
C1: Liquidity Risk Measures
D3: 2021 | E3: 2020 | F3: 2019 | G3: 2018 | H3: 2017
C5: Total Asset | D5: 1259328610 | E5: 992886661 | F5: 833443027 | G5: 706666079 | H5: 662938624
C7: Purchased Funds | D7: 616231172 | E7: 449611987 | F7: 305435633 | G7: 260233987 | H7: 314956748
C8: Purchased Funds /Total Assets | D8: =D7/D5 -> 48.93% | E8: =E7/E5 -> 45.28% | F8: =F7/F5 -> 36.65% | G8: =G7/G5 -> 36.83% | H8: =H7/H5 -> 47.51%
C10: Net Loans | D10: 477673022 | E10: 395416055 | F10: 372913863 | G10: 343107147 | H10: 258693086
C11: Net Loans / Total Assets | D11: =D10/D5 -> 37.93% | E11: =E10/E5 -> 39.82% | F11: =F10/F5 -> 44.74% | G11: =G10/G5 -> 48.55% | H11: =H10/H5 -> 39.02%
C13: Cash and Due from Banks | D13: 89432245 | E13: 73651718 | F13: 63039290 | G13: 49187645 | H13: 44239325
C14: Cash and due from banks/Total asset | D14: =D13/D5 -> 7.10% | E14: =E13/E5 -> 7.42% | F14: =F13/F5 -> 7.56% | G14: =G13/G5 -> 6.96% | H14: =H13/H5 -> 6.67%
C16: Federal Government Security | D16: 593924897 | E16: 429738711 | F16: 284916148 | G16: 249064623 | H16: 303088077
C17: Cash and balances with treasury banks | D17: 89432245 | E17: 73651718 | F17: 63039290 | G17: 49187645 | H17: 44239325
C18: Cash and Government Securities | D18: =D17+D16 -> 683,357,142 | E18: =E17+E16 -> 503,390,429 | F18: =F17+F16 -> 347,955,438 | G18: =G17+G16 -> 298,252,268 | H18: =H17+H16 -> 347,327,402
C19: Cash and Government Securities/TotalAssets | D19: =D18/D5 -> 54.26% | E19: =E18/E5 -> 50.70% | F19: =F18/F5 -> 41.75% | G19: =G18/G5 -> 42.21% | H19: =H18/H5 -> 52.39%

Sheet CAMELS
D1: 2021 | E1: 2020 | F1: 2019 | G1: 2018 | H1: 2017
A3: Capital Adequacy | D3: 0.1338 | E3: 0.1548 | F3: 0.1338 | G3: 0.1251 | H3: 0.1209
A5: Asset Quality
A6: NPL/TL | D6: 0.0614 | E6: 0.0681 | F6: 0.0706 | G6: 0.0722 | H6: 0.0941
A8: Management quality
A9: TL | D9: 477588000000 | E9: 395374000000 | F9: 372914000000 | G9: 343107000000 | H9: 258693000000
A10: No. of Employees | D10: 7478 | E10: 7949 | F10: 7848 | G10: 7538 | H10: 7534
A11: TL/No. of Employees | D11: =D9/D10 -> 63,865,739.50 | E11: =E9/E10 -> 49,738,835.07 | F11: =F9/F10 -> 47,517,074.41 | G11: =G9/G10 -> 45,516,980.63 | H11: =H9/H10 -> 34,336,740.11
A13: Earnings
A14: ROA | D14: 0.77150101 | E14: 1.093478 | F14: 0.84379733 | G14: 0.62669189 | H14: 0.77357041
A15: ROE | D15: 0.17336873 | E15: 0.19855055 | F15: 0.16604406 | G15: 0.1319727 | H15: 0.15778947
A16: NIM | D16: 2.5751457 | E16: 3.0492686 | F16: 2.656033 | G16: 2.6334868 | H16: 2.4429504
A17: Spread | D17: 0.086236481 | E17: 0.12015948 | F17: 0.15219816 | G17: 0.12779737 | H17: 0.080733778
A18: EPS | D18: 0.77093072 | E18: 0.86148852 | F18: 0.55802524 | G18: 0.35140513 | H18: 0.40692367
A20: Liquidity
A21: Cash/Total assets | D21: =[1]BS!B4/[1]BS!B13 -> #ERROR! | E21: =[1]BS!C4/[1]BS!C13 -> #ERROR! | F21: =[1]BS!D4/[1]BS!D13 -> #ERROR! | G21: =[1]BS!E4/[1]BS!E13 -> #ERROR! | H21: =[1]BS!F4/[1]BS!F13 -> #ERROR!
A24: Sensitivity
A25: Shares outstanding | D25: 1260260180 | E25: 1260260180 | F25: 1260260180 | G25: 1260260180 | H25: 1260260180
A26: MV of share | D26: 22.02 | E26: 23.39 | F26: 18.54 | G26: 23.92 | H26: 19.31
A28: MV of equity | D28: =D26*D25/1000 -> 27750929.16 | E28: =E26*E25/1000 -> 29477485.61 | F28: =F26*F25/1000 -> 23365223.74 | G28: =G26*G25/1000 -> 30145423.51 | H28: =H26*H25/1000 -> 24335624.08
A29: Book value of equity | D29: 56040863 | E29: 54681275 | F29: 42353637 | G29: 33557083 | H29: 32500883
A30: BV/MV | D30: =D29/D28 -> 202% | E30: =E29/E28 -> 186% | F30: =F29/F28 -> 181% | G30: =G29/G28 -> 111% | H30: =H29/H28 -> 134%
A33: BV assets
A34: market value of freehold / leasehold land and buildings on freehold / leasehold land | D34: =3874491+5815489+712392+484050 -> 10,886,422.00 | E34: =3737141+5815489+747510+508900 -> 10809040 | F34: =3226063+4797275+785918+535026 -> 9344282 | G34: =3226063+4858175+467177+545698 -> 9,097,113.00 | H34: =2909012+1880715+491179+573737 -> 5,854,643.00 | J34: Rs. In '000
A37: MV sec HTM
A38: BV HTM | D38: 123803338 | E38: 98209659 | F38: 80124923 | G38: 11171395 | H38: 6263449 | J38: Rs. In '000
A39: BV/MV

Sheet Credit Risk Measures
B3: CREDIT RISK MEASURES
B6: 2021 | C6: 2020 | D6: 2019 | E6: 2018 | F6: 2017
A7: Non performing loans | B7: 30952961 | C7: 28410810 | D7: 28133973 | E7: 26657086 | F7: 26753027
A8: Total Loans | B8: 477673022 | C8: 395416055 | D8: 372913863 | E8: 343107147 | F8: 258693086
B9: =B7/B8 -> 6.48% | C9: =C7/C8 -> 7.19% | D9: =D7/D8 -> 7.54% | E9: =E7/E8 -> 7.77% | F9: =F7/F8 -> 10.34%
A11: Net Charge offs | B11: 1043249 | C11: -847 | D11: 637 | E11: 101909 | F11: –
A12: Total Loans | B12: 477673022 | C12: 395416055 | D12: 372913863 | E12: 343107147 | F12: 258693086
B13: =B11/B12 -> 0.2184% | C13: =C11/C12 -> -0.0002% | D13: =D11/D12 -> 0.0002% | E13: =E11/E12 -> 0.0297% | F13: =F11/F12 -> #VALUE!
A15: Provision of loan losses | B15: 28495568 | C15: 24820923 | D15: 24408056 | E15: 25113169 | F15: 24962069
A16: Total Loans | B16: 477673022 | C16: 395416055 | D16: 372913863 | E16: 343107147 | F16: 258693086
B17: =B15/B16 -> 5.97% | C17: =C15/C16 -> 6.28% | D17: =D15/D16 -> 6.55% | E17: =E15/E16 -> 7.32% | F17: =F15/F16 -> 9.65%
A19: Provision of loan losses | B19: 28495568 | C19: 24820923 | D19: 24408056 | E19: 25113169 | F19: 24962069
A20: Equity Capital | B20: 56040863 | C20: 54681275 | D20: 42353637 | E20: 33557083 | F20: 32500883
B21: =B19/B20 -> 50.85% | C21: =C19/C20 -> 45.39% | D21: =D19/D20 -> 57.63% | E21: =E19/E20 -> 74.84% | F21: =F19/F20 -> 76.80%
A23: Non-performing loans | B23: 30952961 | C23: 28410810 | D23: 28133973 | E23: 26657086 | F23: 26753027
A24: Equity Capital | B24: 56040863 | C24: 54681275 | D24: 42353637 | E24: 33557083 | F24: 32500883
B25: =B23/B24 -> 55.23% | C25: =C23/C24 -> 51.96% | D25: =D23/D24 -> 66.43% | E25: =E23/E24 -> 79.44% | F25: =F23/F24 -> 82.31%
A27: Allowance of loan losses
A28: Total Loans | B28: 477673022 | C28: 395416055 | D28: 372913863 | E28: 343107147 | F28: 258693086
B29: =B27/B28 -> - | C29: =C27/C28 -> - | D29: =D27/D28 -> - | E29: =E27/E28 -> - | F29: =F27/F28 -> -
A31: Allowance of loan losses
A32: Equity Capital | B32: 56040863 | C32: 54681275 | D32: 42353637 | E32: 33557083 | F32: 32500883
B33: =B31/B32 -> - | C33: =C31/C32 -> - | D33: =D31/D32 -> - | E33: =E31/E32 -> - | F33: =F31/F32 -> -

Sheet Market Risk
A2: Years | B2: 2021 | C2: 2020 | D2: 2019 | E2: 2018 | F2: 2017
A3: Market Value | B3: =1260260180*22.3 -> 28,103,802,014 | C3: =1260260180*23.39 -> 29,477,485,610 | D3: =1260260180*18.54 -> 23,365,223,737 | E3: =1260260180*23.92 -> 30,145,423,506 | F3: =1260260180*19.31 -> 24,335,624,076
A4: Book Value | B4: 1259328610 | C4: 992886661 | D4: 833443027 | E4: 706666079 | F4: 662938624
A5: Risk | B5: =B4/B3 -> 0.04481 | C5: =C4/C3 -> 0.03368 | D5: =D4/D3 -> 0.03567 | E5: =E4/E3 -> 0.02344 | F5: =F4/F3 -> 0.02724
